{"start":200,"end":400,"index":200,"list":[{"id":520793864704,"key":"KY5103","type":"handu","isError":true},{"id":520855954696,"key":"JM4728","type":"handu","isError":true},{"id":42602269913,"key":"NH4371","type":"handu"},{"id":520515133110,"key":"OZ4548","type":"handu"},{"id":520712665691,"key":"MQ4376","type":"handu"},{"id":520667721048,"key":"HG5377","type":"handu"},{"id":520973290103,"key":"LD5131","type":"handu"},{"id":520959630417,"key":"JW4523","type":"handu"},{"id":520665995325,"key":"JT5041","type":"handu"},{"id":520926078608,"key":"EK5613","type":"handu","isError":true},{"id":520290231901,"key":"HO5140","type":"handu","isError":true},{"id":520438158099,"key":"LU5334","type":"handu"},{"id":520525463139,"key":"HH5120","type":"handu"},{"id":521525324246,"key":"NW5079","type":"handu","isError":true},{"id":40364918662,"key":"HH4083","type":"handu"},{"id":520627169688,"key":"NJ5058","type":"handu"},{"id":520905042403,"key":"JT4724","type":"handu"},{"id":39999640684,"key":"NH2506","type":"handu"},{"id":521062103636,"key":"LD4464","type":"handu"},{"id":521027263301,"key":"YK4261","type":"handu"},{"id":520515310354,"key":"TK5068","type":"handu"},{"id":521033973523,"key":"JN4553","type":"handu","isError":true},{"id":520936529145,"key":"IG5056","type":"handu","isError":true},{"id":44159084118,"key":"OZ4429","type":"handu","isError":true},{"id":521038940697,"key":"MY4713","type":"handu"},{"id":521462883077,"key":"YK4323","type":"handu"},{"id":520418917491,"key":"EK4394","type":"handu"},{"id":520434348416,"key":"LU5315","type":"handu"},{"id":520590183973,"key":"JM4416","type":"handu"},{"id":521027071834,"key":"MM4687","type":"handu"},{"id":521266226278,"key":"MQ4456","type":"handu"},{"id":520715484964,"key":"MY5047","type":"handu"},{"id":521668462953,"key":"GJ5119","type":"handu"},{"id":520419885179,"key":"TK5137","type":"handu"},{"id":520698430241,"key":"DL5152","type":"handu"},{"id":520971153327,"key":"JW5185","type":"handu","isError":true},{"id":521026623141,"key":"JN5102","type":"handu"},{"id":521036942289,"key":"DQ4394","type":"handu"},{"id":520454067754,"key":"NG4930","type":"handu","isError":true},{"id":521039636713,"key":"NW5477","type":"handu","isError":true},{"id":520513972355,"key":"GS4387","type":"handu","isError":true},{"id":520871474265,"key":"HH5027","type":"handu"},{"id":520968855908,"key":"CQ5036","type":"handu"},{"id":520571907943,"key":"OR5955","type":"handu"},{"id":520874326660,"key":"OR5080","type":"handu"},{"id":521039580128,"key":"GQ5057","type":"handu"},{"id":520424312775,"key":"YK5031","type":"handu"},{"id":520491908261,"key":"CQ5119","type":"handu","isError":true},{"id":520364372639,"key":"NW5161","type":"handu"},{"id":520714024374,"key":"LZ4521","type":"handu","isError":true},{"id":521027195578,"key":"JZ5097","type":"handu"},{"id":520811013179,"key":"GS4845","type":"handu"},{"id":520501484053,"key":"TK5814","type":"handu","isError":true},{"id":520798742245,"key":"JN5146","type":"handu"},{"id":521429585279,"key":"YK5275","type":"handu"},{"id":521526586258,"key":"GD4342","type":"handu"},{"id":521036629806,"key":"OR5094","type":"handu"},{"id":520671124820,"key":"MR4932","type":"handu"},{"id":520959782955,"key":"GW4958","type":"handu"},{"id":520557030381,"key":"NH5015","type":"handu"},{"id":521034301516,"key":"NH4637","type":"handu"},{"id":521038908775,"key":"GW5130","type":"handu","isError":true},{"id":520806155036,"key":"MM4883","type":"handu"},{"id":520593106425,"key":"KY4446","type":"handu"},{"id":520711379780,"key":"MY5031","type":"handu"},{"id":520957375910,"key":"AA5086","type":"handu"},{"id":520910976054,"key":"YK4530","type":"handu","isError":true},{"id":521061434827,"key":"IG4351","type":"handu"},{"id":40239338631,"key":"OR4717","type":"handu"},{"id":521037754049,"key":"AA4304","type":"handu","isError":true},{"id":43216492097,"key":"OU4343","type":"handu","isError":true},{"id":45388570899,"key":"EQ5008","type":"handu","isError":true},{"id":520900371453,"key":"RW5091","type":"handu","isError":true},{"id":520958566002,"key":"MQ5039","type":"handu","isError":true},{"id":520574869690,"key":"DU5347","type":"handu"},{"id":520558384158,"key":"YK4380","type":"handu"},{"id":521407457331,"key":"RW4042","type":"handu"},{"id":521543404367,"key":"GS4454","type":"handu","isError":true},{"id":520557924726,"key":"LZ4501","type":"handu"},{"id":40452442160,"key":"DF4039","type":"handu"},{"id":520844671141,"key":"GW5537","type":"handu","isError":true},{"id":521826707103,"key":"LU5305","type":"handu"},{"id":521027627382,"key":"NJ5079","type":"handu"},{"id":520956269232,"key":"JZ4119","type":"handu"},{"id":520851669612,"key":"GY5103","type":"handu","isError":true},{"id":39765955814,"key":"OR4706","type":"handu"},{"id":521226567723,"key":"YK4362","type":"handu"},{"id":521028143158,"key":"PC4488","type":"handu"},{"id":520898581769,"key":"HG4550","type":"handu"},{"id":521247239303,"key":"MR5536","type":"handu"},{"id":520853345783,"key":"MM4774","type":"handu"},{"id":43404084213,"key":"TK4482","type":"handu"},{"id":521035049918,"key":"NG4328","type":"handu"},{"id":40266925288,"key":"IG4105","type":"handu","isError":true},{"id":520713939697,"key":"JZ5540","type":"handu"},{"id":40420289163,"key":"GJ4088","type":"handu"},{"id":521038228822,"key":"JT5552","type":"handu"},{"id":520773369159,"key":"LU5331","type":"handu","isError":true},{"id":520401437046,"key":"TK5812","type":"handu"},{"id":44035561678,"key":"LZ4412","type":"handu"},{"id":520555445331,"key":"MR4198","type":"handu"},{"id":520418843034,"key":"LU5539","type":"handu"},{"id":521261049362,"key":"JW5109","type":"handu","isError":true},{"id":520806195608,"key":"LZ4648","type":"handu"},{"id":40580957861,"key":"DT3290","type":"handu"},{"id":520435931689,"key":"LD5274","type":"handu","isError":true},{"id":520915741756,"key":"NH4701","type":"handu"},{"id":520510904653,"key":"OZ4663","type":"handu"},{"id":520358633342,"key":"PC4478","type":"handu"},{"id":41449953170,"key":"OI4107","type":"handu"},{"id":521034761194,"key":"JQ5130","type":"handu","isError":true},{"id":520669234825,"key":"LD5064","type":"handu"},{"id":521264424899,"key":"RW5134","type":"handu"},{"id":521337529307,"key":"DU4644","type":"handu"},{"id":520956832324,"key":"OI5218","type":"handu","isError":true},{"id":521827768685,"key":"RW4454","type":"handu"},{"id":520810365494,"key":"MM4913","type":"handu","isError":true},{"id":520440685958,"key":"LZ4506","type":"handu"},{"id":520512843629,"key":"DL5007","type":"handu"},{"id":520922933169,"key":"EK4799","type":"handu","isError":true},{"id":520852898371,"key":"GW4845","type":"handu"},{"id":520943433933,"key":"NW4814","type":"handu"},{"id":520959606002,"key":"JW4401","type":"handu"},{"id":521036974856,"key":"EJ5140","type":"handu"},{"id":521525632476,"key":"NG5188","type":"handu","isError":true},{"id":521034277389,"key":"NG4429","type":"handu","isError":true},{"id":521179054101,"key":"GY4420","type":"handu"},{"id":41355175319,"key":"MM4095","type":"handu"},{"id":521035653895,"key":"HG4548","type":"handu","isError":true},{"id":520793892836,"key":"MR4452","type":"handu"},{"id":521037498622,"key":"YK4562","type":"handu"},{"id":520536148927,"key":"JW5176","type":"handu"},{"id":521664110943,"key":"NH4565","type":"handu"},{"id":520513601590,"key":"NG4903","type":"handu"},{"id":520432659773,"key":"GJ5082","type":"handu","isError":true},{"id":521520341723,"key":"HH4914","type":"handu"},{"id":520810133178,"key":"GS4501","type":"handu"},{"id":520435327057,"key":"JM4434","type":"handu"},{"id":520909926983,"key":"GW4928","type":"handu"},{"id":521038332824,"key":"GQ5077","type":"handu"},{"id":521493952294,"key":"YQ5996","type":"handu"},{"id":42568422418,"key":"JM4087","type":"handu"},{"id":520716660262,"key":"OU5142","type":"handu"},{"id":521520073940,"key":"MQ4422","type":"handu"},{"id":521026787357,"key":"GY5102","type":"handu"},{"id":521033733645,"key":"NG4927","type":"handu"},{"id":520974608089,"key":"DL5175","type":"handu"},{"id":521038074418,"key":"LF4285","type":"handu"},{"id":521666988014,"key":"OU5221","type":"handu"},{"id":40573081228,"key":"GJ4021","type":"handu"},{"id":36435434746,"key":"PZ3014","type":"handu"},{"id":521521197286,"key":"JT5651","type":"handu"},{"id":520831123541,"key":"JN5012","type":"handu"},{"id":520624619286,"key":"NH5128","type":"handu"},{"id":520514259031,"key":"GQ4609","type":"handu"},{"id":520940644165,"key":"YQ5079","type":"handu"},{"id":521843096059,"key":"HO4504","type":"handu"},{"id":521520521544,"key":"EK4712","type":"handu"},{"id":520864805427,"key":"MQ4381","type":"handu"},{"id":521041288101,"key":"JT4388","type":"handu"},{"id":520831524323,"key":"EQ4475","type":"handu"},{"id":520918135777,"key":"MM4806","type":"handu","isError":true},{"id":521409036948,"key":"IG4828","type":"handu"},{"id":520902981867,"key":"OR4432","type":"handu"},{"id":521455751848,"key":"OU4624","type":"handu"},{"id":521264544882,"key":"GJ4679","type":"handu"},{"id":521240052554,"key":"NG4934","type":"handu"},{"id":520814956294,"key":"EJ4410","type":"handu"},{"id":40550790666,"key":"HG3266","type":"handu"},{"id":521028827332,"key":"MY4711","type":"handu"},{"id":521411570360,"key":"EK4616","type":"handu"},{"id":520907305318,"key":"GQ4591","type":"handu"},{"id":43143284212,"key":"EK4112","type":"handu"},{"id":520553183307,"key":"GY4307","type":"handu"},{"id":520965003520,"key":"TK5132","type":"handu"},{"id":520628306654,"key":"MR4455","type":"handu"},{"id":40811815008,"key":"RW4235","type":"handu"},{"id":520852876730,"key":"AA5028","type":"handu","isError":true},{"id":520809866047,"key":"JW4579","type":"handu"},{"id":521037830544,"key":"LF5227","type":"handu"},{"id":40950257558,"key":"JM4132","type":"handu"},{"id":521027235009,"key":"DT4759","type":"handu"},{"id":520865783823,"key":"MR5918","type":"handu"},{"id":521464321755,"key":"JN4566","type":"handu"},{"id":521036964396,"key":"GJ4773","type":"handu"},{"id":520692648344,"key":"MQ4434","type":"handu"},{"id":521090591771,"key":"TK4493","type":"handu"},{"id":520839856399,"key":"HH4952","type":"handu"},{"id":521500952280,"key":"OR4849","type":"handu"},{"id":40370887295,"key":"JT4568","type":"handu"},{"id":520506523001,"key":"JQ5097","type":"handu"},{"id":520671588206,"key":"HO4546","type":"handu"},{"id":521033449158,"key":"GJ5136","type":"handu"},{"id":521026795393,"key":"GJ5172","type":"handu","isError":true},{"id":520630520728,"key":"HO4586","type":"handu"},{"id":520497688446,"key":"EK5612","type":"handu"},{"id":521074586665,"key":"NH4525","type":"handu"},{"id":40191132265,"key":"EK3467","type":"handu"},{"id":521041112262,"key":"MM4746","type":"handu"},{"id":521827388864,"key":"JZ5043","type":"handu"}]}